cgcgnet/__init__.py
cgcgnet/featurizer.py
cgcgnet/nn.py
cgcgnet/utils.py
cgcgnet/models/mol2vec_300dim.pkl
cgcgnet-0.1.dist-info/LICENSE
cgcgnet-0.1.dist-info/METADATA
cgcgnet-0.1.dist-info/WHEEL
cgcgnet-0.1.dist-info/top_level.txt
cgcgnet-0.1.dist-info/RECORD
